.DS_Store
TurkishStemmer/.DS_Store
TurkishStemmer/__init__.py
TurkishStemmer/resources/__init__.py
TurkishStemmer/resources/average_stem_size_exceptions.txt
TurkishStemmer/resources/last_consonant_exceptions.txt
TurkishStemmer/resources/protected_words.txt
TurkishStemmer/resources/vowel_harmony_exceptions.txt
TurkishStemmer/states/DerivationalState.py
TurkishStemmer/states/NominalVerbState.py
TurkishStemmer/states/NounState.py
TurkishStemmer/states/__init__.py
TurkishStemmer/suffixes/DerivationalSuffix.py
TurkishStemmer/suffixes/NominalVerbSuffix.py
TurkishStemmer/suffixes/NounSuffix.py
TurkishStemmer/suffixes/__init__.py
TurkishStemmer/transitions/__init__.py
TurkishStemmer-1.3.dist-info/LICENSE.txt
TurkishStemmer-1.3.dist-info/METADATA
TurkishStemmer-1.3.dist-info/WHEEL
TurkishStemmer-1.3.dist-info/top_level.txt
TurkishStemmer-1.3.dist-info/RECORD
