Metadata-Version: 2.1
Name: TurkishStemmer
Version: 1.3
Summary: Turkish Stemmer
Home-page: https://github.com/hanefi/turkish-stemmer-python
Author: Hanefi Onaldi
Author-email: abdullahanefi16@gmail.com
License: UNKNOWN
Platform: UNKNOWN
